botbuilder/core/__init__.py
botbuilder/core/about.py
botbuilder/core/activity_handler.py
botbuilder/core/adapter_extensions.py
botbuilder/core/auto_save_state_middleware.py
botbuilder/core/bot.py
botbuilder/core/bot_adapter.py
botbuilder/core/bot_assert.py
botbuilder/core/bot_framework_adapter.py
botbuilder/core/bot_state.py
botbuilder/core/bot_state_set.py
botbuilder/core/bot_telemetry_client.py
botbuilder/core/card_factory.py
botbuilder/core/channel_service_handler.py
botbuilder/core/cloud_adapter_base.py
botbuilder/core/cloud_channel_service_handler.py
botbuilder/core/component_registration.py
botbuilder/core/conversation_reference_extension.py
botbuilder/core/conversation_state.py
botbuilder/core/intent_score.py
botbuilder/core/invoke_response.py
botbuilder/core/memory_storage.py
botbuilder/core/memory_transcript_store.py
botbuilder/core/message_factory.py
botbuilder/core/middleware_set.py
botbuilder/core/null_telemetry_client.py
botbuilder/core/private_conversation_state.py
botbuilder/core/property_manager.py
botbuilder/core/queue_storage.py
botbuilder/core/re_escape.py
botbuilder/core/recognizer.py
botbuilder/core/recognizer_result.py
botbuilder/core/register_class_middleware.py
botbuilder/core/serializer_helper.py
botbuilder/core/show_typing_middleware.py
botbuilder/core/state_property_accessor.py
botbuilder/core/state_property_info.py
botbuilder/core/storage.py
botbuilder/core/telemetry_constants.py
botbuilder/core/telemetry_logger_constants.py
botbuilder/core/telemetry_logger_middleware.py
botbuilder/core/transcript_logger.py
botbuilder/core/turn_context.py
botbuilder/core/user_state.py
botbuilder/core/adapters/__init__.py
botbuilder/core/adapters/test_adapter.py
botbuilder/core/inspection/__init__.py
botbuilder/core/inspection/inspection_middleware.py
botbuilder/core/inspection/inspection_session.py
botbuilder/core/inspection/inspection_sessions_by_status.py
botbuilder/core/inspection/inspection_state.py
botbuilder_core-4.15.1.dist-info/METADATA
botbuilder_core-4.15.1.dist-info/WHEEL
botbuilder_core-4.15.1.dist-info/top_level.txt
botbuilder_core-4.15.1.dist-info/RECORD
